.DS_Store
searchbar_component/.DS_Store
searchbar_component/__init__.py
searchbar_component/example.py
searchbar_component/highlight.py
searchbar_component/frontend/.DS_Store
searchbar_component/frontend/build/.DS_Store
searchbar_component/frontend/build/asset-manifest.json
searchbar_component/frontend/build/bootstrap.min.css
searchbar_component/frontend/build/index.html
searchbar_component/frontend/build/static/.DS_Store
searchbar_component/frontend/build/static/css/main.041c206f.css
searchbar_component/frontend/build/static/css/main.041c206f.css.map
searchbar_component/frontend/build/static/css/main.2d695fab.css
searchbar_component/frontend/build/static/css/main.2d695fab.css.map
searchbar_component/frontend/build/static/js/main.0b43c012.js
searchbar_component/frontend/build/static/js/main.0b43c012.js.LICENSE.txt
searchbar_component/frontend/build/static/js/main.0b43c012.js.map
searchbar_component/frontend/build/static/js/main.26cd9672.js
searchbar_component/frontend/build/static/js/main.26cd9672.js.LICENSE.txt
searchbar_component/frontend/build/static/js/main.26cd9672.js.map
searchbar_component/frontend/build/static/js/main.3fcdf5bb.js
searchbar_component/frontend/build/static/js/main.3fcdf5bb.js.LICENSE.txt
searchbar_component/frontend/build/static/js/main.3fcdf5bb.js.map
searchbar_component/frontend/build/static/js/main.948d924c.js
searchbar_component/frontend/build/static/js/main.948d924c.js.LICENSE.txt
searchbar_component/frontend/build/static/js/main.948d924c.js.map
searchbar_component/frontend/build/static/js/main.be38a022.js
searchbar_component/frontend/build/static/js/main.be38a022.js.LICENSE.txt
searchbar_component/frontend/build/static/js/main.be38a022.js.map
searchbar_component/frontend/build/static/js/main.e6321e9a.js
searchbar_component/frontend/build/static/js/main.e6321e9a.js.LICENSE.txt
searchbar_component/frontend/build/static/js/main.e6321e9a.js.map
searchbar_component-0.2.7.dist-info/LICENSE
searchbar_component-0.2.7.dist-info/METADATA
searchbar_component-0.2.7.dist-info/WHEEL
searchbar_component-0.2.7.dist-info/top_level.txt
searchbar_component-0.2.7.dist-info/RECORD
