Metadata-Version: 2.1
Name: searchbar_component
Version: 0.2.7
Summary: A Streamlit component for a search bar with autosuggestions
Home-page: https://github.com/weeks888/searchbar_component
Author: chris weeks
License: MIT
Keywords: streamlit component searchbar autocomplete
Classifier: Development Status :: 4 - Beta
Classifier: Intended Audience :: Developers
Classifier: License :: OSI Approved :: MIT License
Classifier: Operating System :: OS Independent
Classifier: Programming Language :: Python :: 3
Classifier: Programming Language :: Python :: 3.7
Classifier: Programming Language :: Python :: 3.8
Classifier: Programming Language :: Python :: 3.9
Classifier: Programming Language :: Python :: 3.10
Classifier: Programming Language :: Python :: 3.11
Requires-Python: >=3.7
License-File: LICENSE
Requires-Dist: streamlit >=0.63
